Metadata-Version: 1.2
Name: opgg-helper
Version: 0.0.1
Summary: CLI tool for increase accessibility to OP.GG stats
Home-page: https://github.com/JoMingyu/opgg-helper
Author: PlanB
Author-email: mingyu.planb@gmail.com
Maintainer: PlanB
Maintainer-email: mingyu.planb@gmail.com
License: MIT License
Platform: UNKNOWN
Classifier: Programming Language :: Python
Classifier: Programming Language :: Python :: 3
Classifier: Topic :: Software Development :: Libraries :: Python Modules
